{"title":"物理“声的传播”例题分享","uid":"9b767e0c0dbe490fefea07749303c21c","slug":"物理例题分享[1]","date":"2022-12-04T08:11:05.000Z","updated":"2023-06-24T07:21:35.300Z","comments":true,"path":"api/articles/物理例题分享[1].json","keywords":"Limit-Blog","cover":"https://pic.imgdb.cn/item/648eb0561ddac507cc7c45c1.jpg","content":"<h3 id=\"提示：本文章将要讲的是初中物理中有关“声的传播”的基本例题分享\"><a href=\"#提示：本文章将要讲的是初中物理中有关“声的传播”的基本例题分享\" class=\"headerlink\" title=\"提示：本文章将要讲的是初中物理中有关“声的传播”的基本例题分享\"></a>提示：本文章将要讲的是初中物理中有关“声的传播”的基本例题分享</h3><h2 id=\"【例-1】\"><a href=\"#【例-1】\" class=\"headerlink\" title=\"【例 1】\"></a>【例 1】</h2><h3 id=\"如图-1-1-所示，-声源-S-和观察者-A-都沿-x-轴正方向运动，-相对与地面的速率分别为-Vs-和-Va，-空气中声音的传播速率为-Vp，-设-Vs-lt-Vp，-Va-lt-Vp，-空气相对于地面没有流动。\"><a href=\"#如图-1-1-所示，-声源-S-和观察者-A-都沿-x-轴正方向运动，-相对与地面的速率分别为-Vs-和-Va，-空气中声音的传播速率为-Vp，-设-Vs-lt-Vp，-Va-lt-Vp，-空气相对于地面没有流动。\" class=\"headerlink\" title=\"如图 1.1 所示， 声源 S 和观察者 A 都沿 x 轴正方向运动， 相对与地面的速率分别为 Vs 和 Va， 空气中声音的传播速率为 Vp， 设 Vs &lt; Vp， Va &lt; Vp， 空气相对于地面没有流动。\"></a>如图 1.1 所示， 声源 S 和观察者 A 都沿 x 轴正方向运动， 相对与地面的速率分别为 Vs 和 Va， 空气中声音的传播速率为 Vp， 设 Vs &lt; Vp， Va &lt; Vp， 空气相对于地面没有流动。</h3><img src = \"https://pic.imgdb.cn/item/638c5e9b16f2c2beb18c1895.png\" alt = \"1.1\">\n\n<h3 id=\"（1）-若声源相继发出两个声信号，时间间隔为-Δt，-请根据发出的这两个声信号从声源传播到观察者的过程，-确定观察者接收到这两个声信号的时间间隔-Δt’。\"><a href=\"#（1）-若声源相继发出两个声信号，时间间隔为-Δt，-请根据发出的这两个声信号从声源传播到观察者的过程，-确定观察者接收到这两个声信号的时间间隔-Δt’。\" class=\"headerlink\" title=\"（1） 若声源相继发出两个声信号，时间间隔为 Δt， 请根据发出的这两个声信号从声源传播到观察者的过程， 确定观察者接收到这两个声信号的时间间隔 Δt’。\"></a>（1） 若声源相继发出两个声信号，时间间隔为 Δt， 请根据发出的这两个声信号从声源传播到观察者的过程， 确定观察者接收到这两个声信号的时间间隔 Δt’。</h3><h2 id=\"【解析】\"><a href=\"#【解析】\" class=\"headerlink\" title=\"【解析】\"></a>【解析】</h2><h3 id=\"（1）设-t1，-t2-为声源-S-发出的两个信号的时刻，-t1’，-t2’-为观察者接收到两个信号的时刻。-则第一个信号经过-t1’-t1-时间被观察者-A-接收到，-第二个信号经过-t2’-t2-时间被观察者-A-接收到，-且-t2-t1-Δt，-t2’-t1’-Δt’。-设声源发出的第一个信号时，-S-和-A-间的距离为-L，-两个声信号从声源传播到观察者的过程中，-它们的远动的距离关系如图-1-2-和-1-3-所示。\"><a href=\"#（1）设-t1，-t2-为声源-S-发出的两个信号的时刻，-t1’，-t2’-为观察者接收到两个信号的时刻。-则第一个信号经过-t1’-t1-时间被观察者-A-接收到，-第二个信号经过-t2’-t2-时间被观察者-A-接收到，-且-t2-t1-Δt，-t2’-t1’-Δt’。-设声源发出的第一个信号时，-S-和-A-间的距离为-L，-两个声信号从声源传播到观察者的过程中，-它们的远动的距离关系如图-1-2-和-1-3-所示。\" class=\"headerlink\" title=\"（1）设 t1， t2 为声源 S 发出的两个信号的时刻， t1’， t2’ 为观察者接收到两个信号的时刻。 则第一个信号经过 t1’ - t1 时间被观察者 A 接收到， 第二个信号经过 t2’ - t2 时间被观察者 A 接收到， 且 t2 - t1 = Δt， t2’ - t1’ = Δt’。 设声源发出的第一个信号时， S 和 A 间的距离为 L， 两个声信号从声源传播到观察者的过程中， 它们的远动的距离关系如图 1.2 和 1.3 所示。\"></a>（1）设 t1， t2 为声源 S 发出的两个信号的时刻， t1’， t2’ 为观察者接收到两个信号的时刻。 则第一个信号经过 t1’ - t1 时间被观察者 A 接收到， 第二个信号经过 t2’ - t2 时间被观察者 A 接收到， 且 t2 - t1 = Δt， t2’ - t1’ = Δt’。 设声源发出的第一个信号时， S 和 A 间的距离为 L， 两个声信号从声源传播到观察者的过程中， 它们的远动的距离关系如图 1.2 和 1.3 所示。</h3><img src = \"https://pic.imgdb.cn/item/638c5ea916f2c2beb18c2b0f.png\" alt = \"1.2\">\n\n<img src = \"https://pic.imgdb.cn/item/638c5eb516f2c2beb18c3ad9.png\" alt = \"1.3\">\n\n<h3 id=\"于是，-可得：\"><a href=\"#于是，-可得：\" class=\"headerlink\" title=\"于是， 可得：\"></a>于是， 可得：</h3><h3 id=\"1-Vp-t1’-t1-L-Va-t1’-t1\"><a href=\"#1-Vp-t1’-t1-L-Va-t1’-t1\" class=\"headerlink\" title=\"1. Vp(t1’ - t1) = L + Va(t1’ - t1)\"></a>1. Vp(t1’ - t1) = L + Va(t1’ - t1)</h3><h3 id=\"2-Vp-t2’-t2-L-Va-t2’-t1-VsΔt\"><a href=\"#2-Vp-t2’-t2-L-Va-t2’-t1-VsΔt\" class=\"headerlink\" title=\"2. Vp(t2’ - t2) = L + Va(t2’ - t1) - VsΔt\"></a>2. Vp(t2’ - t2) = L + Va(t2’ - t1) - VsΔt</h3><h3 id=\"由以上两式解得：\"><a href=\"#由以上两式解得：\" class=\"headerlink\" title=\"由以上两式解得：\"></a>由以上两式解得：</h3><h3 id=\"Δt’-Vp-Vs-Δt-Vp-Va\"><a href=\"#Δt’-Vp-Vs-Δt-Vp-Va\" class=\"headerlink\" title=\"Δt’ = (Vp - Vs)Δt / (Vp - Va)\"></a>Δt’ = (Vp - Vs)Δt / (Vp - Va)</h3><h4 id=\"此文章仅供参考，如有疑问，请发送邮件至-2966653003-qq-com，-谢谢\"><a href=\"#此文章仅供参考，如有疑问，请发送邮件至-2966653003-qq-com，-谢谢\" class=\"headerlink\" title=\"此文章仅供参考，如有疑问，请发送邮件至 2966653003@qq.com， 谢谢!\"></a>此文章仅供参考，如有疑问，请发送邮件至 <a href=\"\">2966653003@qq.com</a>， 谢谢!</h4>","text":"提示：本文章将要讲的是初中物理中有关“声的传播”的基本例题分享【例 1】如图 1.1 所示， 声源 S 和观察者 A 都沿 x 轴正方向运动， 相对与地面的速率分别为 Vs 和 Va， 空气中声音的传播速率为 Vp， 设 Vs &lt; Vp， Va &lt; Vp， 空气相对于...","link":"","photos":[],"count_time":{"symbolsCount":621,"symbolsTime":"1 mins."},"categories":[{"name":"学术","slug":"学术","count":2,"path":"api/categories/学术.json"}],"tags":[{"name":"物理","slug":"物理","count":1,"path":"api/tags/物理.json"},{"name":"学习笔记","slug":"学习笔记","count":1,"path":"api/tags/学习笔记.json"}],"toc":"<ol class=\"toc\"><li class=\"toc-item toc-level-3\"><a class=\"toc-link\" href=\"#%E6%8F%90%E7%A4%BA%EF%BC%9A%E6%9C%AC%E6%96%87%E7%AB%A0%E5%B0%86%E8%A6%81%E8%AE%B2%E7%9A%84%E6%98%AF%E5%88%9D%E4%B8%AD%E7%89%A9%E7%90%86%E4%B8%AD%E6%9C%89%E5%85%B3%E2%80%9C%E5%A3%B0%E7%9A%84%E4%BC%A0%E6%92%AD%E2%80%9D%E7%9A%84%E5%9F%BA%E6%9C%AC%E4%BE%8B%E9%A2%98%E5%88%86%E4%BA%AB\"><span class=\"toc-text\">提示：本文章将要讲的是初中物理中有关“声的传播”的基本例题分享</span></a></li></ol></li><li class=\"toc-item toc-level-2\"><a class=\"toc-link\" href=\"#%E3%80%90%E4%BE%8B-1%E3%80%91\"><span class=\"toc-text\">【例 1】</span></a><ol class=\"toc-child\"><li class=\"toc-item toc-level-3\"><a class=\"toc-link\" href=\"#%E5%A6%82%E5%9B%BE-1-1-%E6%89%80%E7%A4%BA%EF%BC%8C-%E5%A3%B0%E6%BA%90-S-%E5%92%8C%E8%A7%82%E5%AF%9F%E8%80%85-A-%E9%83%BD%E6%B2%BF-x-%E8%BD%B4%E6%AD%A3%E6%96%B9%E5%90%91%E8%BF%90%E5%8A%A8%EF%BC%8C-%E7%9B%B8%E5%AF%B9%E4%B8%8E%E5%9C%B0%E9%9D%A2%E7%9A%84%E9%80%9F%E7%8E%87%E5%88%86%E5%88%AB%E4%B8%BA-Vs-%E5%92%8C-Va%EF%BC%8C-%E7%A9%BA%E6%B0%94%E4%B8%AD%E5%A3%B0%E9%9F%B3%E7%9A%84%E4%BC%A0%E6%92%AD%E9%80%9F%E7%8E%87%E4%B8%BA-Vp%EF%BC%8C-%E8%AE%BE-Vs-lt-Vp%EF%BC%8C-Va-lt-Vp%EF%BC%8C-%E7%A9%BA%E6%B0%94%E7%9B%B8%E5%AF%B9%E4%BA%8E%E5%9C%B0%E9%9D%A2%E6%B2%A1%E6%9C%89%E6%B5%81%E5%8A%A8%E3%80%82\"><span class=\"toc-text\">如图 1.1 所示， 声源 S 和观察者 A 都沿 x 轴正方向运动， 相对与地面的速率分别为 Vs 和 Va， 空气中声音的传播速率为 Vp， 设 Vs &lt; Vp， Va &lt; Vp， 空气相对于地面没有流动。</span></a></li><li class=\"toc-item toc-level-3\"><a class=\"toc-link\" href=\"#%EF%BC%881%EF%BC%89-%E8%8B%A5%E5%A3%B0%E6%BA%90%E7%9B%B8%E7%BB%A7%E5%8F%91%E5%87%BA%E4%B8%A4%E4%B8%AA%E5%A3%B0%E4%BF%A1%E5%8F%B7%EF%BC%8C%E6%97%B6%E9%97%B4%E9%97%B4%E9%9A%94%E4%B8%BA-%CE%94t%EF%BC%8C-%E8%AF%B7%E6%A0%B9%E6%8D%AE%E5%8F%91%E5%87%BA%E7%9A%84%E8%BF%99%E4%B8%A4%E4%B8%AA%E5%A3%B0%E4%BF%A1%E5%8F%B7%E4%BB%8E%E5%A3%B0%E6%BA%90%E4%BC%A0%E6%92%AD%E5%88%B0%E8%A7%82%E5%AF%9F%E8%80%85%E7%9A%84%E8%BF%87%E7%A8%8B%EF%BC%8C-%E7%A1%AE%E5%AE%9A%E8%A7%82%E5%AF%9F%E8%80%85%E6%8E%A5%E6%94%B6%E5%88%B0%E8%BF%99%E4%B8%A4%E4%B8%AA%E5%A3%B0%E4%BF%A1%E5%8F%B7%E7%9A%84%E6%97%B6%E9%97%B4%E9%97%B4%E9%9A%94-%CE%94t%E2%80%99%E3%80%82\"><span class=\"toc-text\">（1） 若声源相继发出两个声信号，时间间隔为 Δt， 请根据发出的这两个声信号从声源传播到观察者的过程， 确定观察者接收到这两个声信号的时间间隔 Δt’。</span></a></li></ol></li><li class=\"toc-item toc-level-2\"><a class=\"toc-link\" href=\"#%E3%80%90%E8%A7%A3%E6%9E%90%E3%80%91\"><span class=\"toc-text\">【解析】</span></a><ol class=\"toc-child\"><li class=\"toc-item toc-level-3\"><a class=\"toc-link\" href=\"#%EF%BC%881%EF%BC%89%E8%AE%BE-t1%EF%BC%8C-t2-%E4%B8%BA%E5%A3%B0%E6%BA%90-S-%E5%8F%91%E5%87%BA%E7%9A%84%E4%B8%A4%E4%B8%AA%E4%BF%A1%E5%8F%B7%E7%9A%84%E6%97%B6%E5%88%BB%EF%BC%8C-t1%E2%80%99%EF%BC%8C-t2%E2%80%99-%E4%B8%BA%E8%A7%82%E5%AF%9F%E8%80%85%E6%8E%A5%E6%94%B6%E5%88%B0%E4%B8%A4%E4%B8%AA%E4%BF%A1%E5%8F%B7%E7%9A%84%E6%97%B6%E5%88%BB%E3%80%82-%E5%88%99%E7%AC%AC%E4%B8%80%E4%B8%AA%E4%BF%A1%E5%8F%B7%E7%BB%8F%E8%BF%87-t1%E2%80%99-t1-%E6%97%B6%E9%97%B4%E8%A2%AB%E8%A7%82%E5%AF%9F%E8%80%85-A-%E6%8E%A5%E6%94%B6%E5%88%B0%EF%BC%8C-%E7%AC%AC%E4%BA%8C%E4%B8%AA%E4%BF%A1%E5%8F%B7%E7%BB%8F%E8%BF%87-t2%E2%80%99-t2-%E6%97%B6%E9%97%B4%E8%A2%AB%E8%A7%82%E5%AF%9F%E8%80%85-A-%E6%8E%A5%E6%94%B6%E5%88%B0%EF%BC%8C-%E4%B8%94-t2-t1-%CE%94t%EF%BC%8C-t2%E2%80%99-t1%E2%80%99-%CE%94t%E2%80%99%E3%80%82-%E8%AE%BE%E5%A3%B0%E6%BA%90%E5%8F%91%E5%87%BA%E7%9A%84%E7%AC%AC%E4%B8%80%E4%B8%AA%E4%BF%A1%E5%8F%B7%E6%97%B6%EF%BC%8C-S-%E5%92%8C-A-%E9%97%B4%E7%9A%84%E8%B7%9D%E7%A6%BB%E4%B8%BA-L%EF%BC%8C-%E4%B8%A4%E4%B8%AA%E5%A3%B0%E4%BF%A1%E5%8F%B7%E4%BB%8E%E5%A3%B0%E6%BA%90%E4%BC%A0%E6%92%AD%E5%88%B0%E8%A7%82%E5%AF%9F%E8%80%85%E7%9A%84%E8%BF%87%E7%A8%8B%E4%B8%AD%EF%BC%8C-%E5%AE%83%E4%BB%AC%E7%9A%84%E8%BF%9C%E5%8A%A8%E7%9A%84%E8%B7%9D%E7%A6%BB%E5%85%B3%E7%B3%BB%E5%A6%82%E5%9B%BE-1-2-%E5%92%8C-1-3-%E6%89%80%E7%A4%BA%E3%80%82\"><span class=\"toc-text\">（1）设 t1， t2 为声源 S 发出的两个信号的时刻， t1’， t2’ 为观察者接收到两个信号的时刻。 则第一个信号经过 t1’ - t1 时间被观察者 A 接收到， 第二个信号经过 t2’ - t2 时间被观察者 A 接收到， 且 t2 - t1 &#x3D; Δt， t2’ - t1’ &#x3D; Δt’。 设声源发出的第一个信号时， S 和 A 间的距离为 L， 两个声信号从声源传播到观察者的过程中， 它们的远动的距离关系如图 1.2 和 1.3 所示。</span></a></li><li class=\"toc-item toc-level-3\"><a class=\"toc-link\" href=\"#%E4%BA%8E%E6%98%AF%EF%BC%8C-%E5%8F%AF%E5%BE%97%EF%BC%9A\"><span class=\"toc-text\">于是， 可得：</span></a></li><li class=\"toc-item toc-level-3\"><a class=\"toc-link\" href=\"#1-Vp-t1%E2%80%99-t1-L-Va-t1%E2%80%99-t1\"><span class=\"toc-text\">1. Vp(t1’ - t1) &#x3D; L + Va(t1’ - t1)</span></a></li><li class=\"toc-item toc-level-3\"><a class=\"toc-link\" href=\"#2-Vp-t2%E2%80%99-t2-L-Va-t2%E2%80%99-t1-Vs%CE%94t\"><span class=\"toc-text\">2. Vp(t2’ - t2) &#x3D; L + Va(t2’ - t1) - VsΔt</span></a></li><li class=\"toc-item toc-level-3\"><a class=\"toc-link\" href=\"#%E7%94%B1%E4%BB%A5%E4%B8%8A%E4%B8%A4%E5%BC%8F%E8%A7%A3%E5%BE%97%EF%BC%9A\"><span class=\"toc-text\">由以上两式解得：</span></a></li><li class=\"toc-item toc-level-3\"><a class=\"toc-link\" href=\"#%CE%94t%E2%80%99-Vp-Vs-%CE%94t-Vp-Va\"><span class=\"toc-text\">Δt’ &#x3D; (Vp - Vs)Δt &#x2F; (Vp - Va)</span></a><ol class=\"toc-child\"><li class=\"toc-item toc-level-4\"><a class=\"toc-link\" href=\"#%E6%AD%A4%E6%96%87%E7%AB%A0%E4%BB%85%E4%BE%9B%E5%8F%82%E8%80%83%EF%BC%8C%E5%A6%82%E6%9C%89%E7%96%91%E9%97%AE%EF%BC%8C%E8%AF%B7%E5%8F%91%E9%80%81%E9%82%AE%E4%BB%B6%E8%87%B3-2966653003-qq-com%EF%BC%8C-%E8%B0%A2%E8%B0%A2\"><span class=\"toc-text\">此文章仅供参考，如有疑问，请发送邮件至 2966653003@qq.com， 谢谢!</span></a></li></ol></li></ol>","author":{"name":"Scorpio","slug":"blog-author","avatar":"https://pic.imgdb.cn/item/63fb3165f144a010072484b1.png","link":"/","description":"一位正在享受生活的小伙","socials":{"github":"https://github.com/Scorpio-Limit","twitter":"","stackoverflow":"","wechat":"","qq":"","weibo":"","zhihu":"https://www.zhihu.com/people/lonely-scorpio-11","csdn":"","juejin":"","customs":{"bilibili":{"icon":"/svg/bilibili.svg","link":"https://space.bilibili.com/1179082277"}}}},"mapped":true,"prev_post":{"title":"2018年刑侦科推理试题讲解","uid":"365f8d660f31d41852d831b89da3e2a8","slug":"2018年刑侦科推理试题讲解","date":"2023-01-26T06:38:13.000Z","updated":"2023-06-24T07:21:45.903Z","comments":true,"path":"api/articles/2018年刑侦科推理试题讲解.json","keywords":"Limit-Blog","cover":"https://cdn.luogu.com.cn/upload/image_hosting/yr9wzjn4.png","text":"提示：本文章将讲解 《2018年刑侦科推理试题》 的解题过程 首先看看题就知道这 10 道题目之间相互有线索关联着。第一轮查找线索：（找出题面话语背后的意思）第1题：找不到有用的线索，答案应该是根据其它题目确定的；第2题：说答案是第5题的答案，但是答案的排列完全不同（A.C B....","link":"","photos":[],"count_time":{"symbolsCount":"2.5k","symbolsTime":"2 mins."},"categories":[{"name":"学术","slug":"学术","count":2,"path":"api/categories/学术.json"}],"tags":[{"name":"讲解","slug":"讲解","count":1,"path":"api/tags/讲解.json"},{"name":"逻辑推理","slug":"逻辑推理","count":1,"path":"api/tags/逻辑推理.json"},{"name":"刑侦科","slug":"刑侦科","count":1,"path":"api/tags/刑侦科.json"},{"name":"2018年刑侦科推理试题","slug":"2018年刑侦科推理试题","count":1,"path":"api/tags/2018年刑侦科推理试题.json"}],"author":{"name":"Scorpio","slug":"blog-author","avatar":"https://pic.imgdb.cn/item/63fb3165f144a010072484b1.png","link":"/","description":"一位正在享受生活的小伙","socials":{"github":"https://github.com/Scorpio-Limit","twitter":"","stackoverflow":"","wechat":"","qq":"","weibo":"","zhihu":"https://www.zhihu.com/people/lonely-scorpio-11","csdn":"","juejin":"","customs":{"bilibili":{"icon":"/svg/bilibili.svg","link":"https://space.bilibili.com/1179082277"}}}}},"next_post":{"title":"CF1730A题解","uid":"b8278ec2c4d426b09bc57c8661224203","slug":"Codeforces-Round823(Div. 2)[A.Planets]","date":"2022-09-30T10:23:17.000Z","updated":"2023-06-24T07:21:38.426Z","comments":true,"path":"api/articles/Codeforces-Round823(Div. 2)[A.Planets].json","keywords":"Limit-Blog","cover":"https://cdn.luogu.com.cn/upload/image_hosting/snxd72tx.png","text":"Codeforces Round #823 (Div. 2) A.Plantes 题解原题链接题目大意题意大致是: 在 n 条轨道里, 每一条轨道上都有一些星球(即障碍物), 且第 i 条轨道上共有 a[i] 个障碍物.现在有两台可以消灭障碍物的机器 A 和 B.机器 A 一次性...","link":"","photos":[],"count_time":{"symbolsCount":"1.2k","symbolsTime":"1 mins."},"categories":[{"name":"Problem-Explanation","slug":"Problem-Explanation","count":6,"path":"api/categories/Problem-Explanation.json"}],"tags":[{"name":"Codeforces","slug":"Codeforces","count":3,"path":"api/tags/Codeforces.json"}],"author":{"name":"Scorpio","slug":"blog-author","avatar":"https://pic.imgdb.cn/item/63fb3165f144a010072484b1.png","link":"/","description":"一位正在享受生活的小伙","socials":{"github":"https://github.com/Scorpio-Limit","twitter":"","stackoverflow":"","wechat":"","qq":"","weibo":"","zhihu":"https://www.zhihu.com/people/lonely-scorpio-11","csdn":"","juejin":"","customs":{"bilibili":{"icon":"/svg/bilibili.svg","link":"https://space.bilibili.com/1179082277"}}}}}}